onnxruntime-1.18.0.dist-info/WHEEL
onnxruntime-1.18.0.dist-info/top_level.txt
onnxruntime-1.18.0.dist-info/entry_points.txt
onnxruntime-1.18.0.dist-info/RECORD
onnxruntime-1.18.0.dist-info/METADATA
onnxruntime/Privacy.md
onnxruntime/__init__.py
onnxruntime/LICENSE
onnxruntime/ThirdPartyNotices.txt
onnxruntime/datasets/__init__.py
onnxruntime/datasets/sigmoid.onnx
onnxruntime/datasets/logreg_iris.onnx
onnxruntime/datasets/mul_1.onnx
onnxruntime/tools/onnx_randomizer.py
onnxruntime/tools/__init__.py
onnxruntime/tools/make_dynamic_shape_fixed.py
onnxruntime/tools/optimize_onnx_model.py
onnxruntime/tools/offline_tuning.py
onnxruntime/tools/logger.py
onnxruntime/tools/check_onnx_model_mobile_usability.py
onnxruntime/tools/file_utils.py
onnxruntime/tools/convert_onnx_models_to_ort.py
onnxruntime/tools/onnx_model_utils.py
onnxruntime/tools/onnxruntime_test.py
onnxruntime/tools/symbolic_shape_infer.py
onnxruntime/tools/update_onnx_opset.py
onnxruntime/tools/reduced_build_config_parser.py
onnxruntime/tools/pytorch_export_contrib_ops.py
onnxruntime/tools/pytorch_export_helpers.py
onnxruntime/tools/mobile_helpers/__init__.py
onnxruntime/tools/mobile_helpers/check_model_can_use_ort_mobile_pkg.py
onnxruntime/tools/mobile_helpers/usability_checker.py
onnxruntime/tools/mobile_helpers/coreml_supported_ops.md
onnxruntime/tools/mobile_helpers/nnapi_supported_ops.md
onnxruntime/tools/mobile_helpers/mobile_package.required_operators.config
onnxruntime/tools/ort_format_model/__init__.py
onnxruntime/tools/ort_format_model/ort_model_processor.py
onnxruntime/tools/ort_format_model/utils.py
onnxruntime/tools/ort_format_model/operator_type_usage_processors.py
onnxruntime/tools/ort_format_model/types.py
onnxruntime/tools/ort_format_model/ort_flatbuffers_py/__init__.py
onnxruntime/tools/ort_format_model/ort_flatbuffers_py/fbs/Tensor.py
onnxruntime/tools/ort_format_model/ort_flatbuffers_py/fbs/NodeEdge.py
onnxruntime/tools/ort_format_model/ort_flatbuffers_py/fbs/IntProperty.py
onnxruntime/tools/ort_format_model/ort_flatbuffers_py/fbs/DeprecatedNodeIndexAndKernelDefHash.py
