Metadata-Version: 2.1
Name: onnxruntime
Version: 1.18.0
Summary: ONNX Runtime is a runtime accelerator for Machine Learning models
Home-page: https://onnxruntime.ai
Download-URL: https://github.com/microsoft/onnxruntime/tags
Author: Microsoft Corporation
Author-email: onnxruntime@microsoft.com
License: MIT License
Keywords: onnx machine learning
Classifier: Development Status :: 5 - Production/Stable
Classifier: Intended Audience :: Developers
Classifier: License :: OSI Approved :: MIT License
Classifier: Operating System :: POSIX :: Linux
Classifier: Topic :: Scientific/Engineering
Classifier: Topic :: Scientific/Engineering :: Mathematics
Classifier: Topic :: Scientific/Engineering :: Artificial Intelligence
Classifier: Topic :: Software Development
Classifier: Topic :: Software Development :: Libraries
Classifier: Topic :: Software Development :: Libraries :: Python Modules
Classifier: Programming Language :: Python
Classifier: Programming Language :: Python :: 3 :: Only
Classifier: Programming Language :: Python :: 3.7
Classifier: Programming Language :: Python :: 3.8
Classifier: Programming Language :: Python :: 3.9
Classifier: Programming Language :: Python :: 3.10
Classifier: Programming Language :: Python :: 3.11
Classifier: Programming Language :: Python :: 3.12
Classifier: Operating System :: Microsoft :: Windows
Classifier: Operating System :: MacOS
Requires-Dist: coloredlogs
Requires-Dist: flatbuffers
Requires-Dist: numpy >=1.24.2
Requires-Dist: packaging
Requires-Dist: protobuf
Requires-Dist: sympy
